atup/__init__.py
atup/_modidx.py
atup/atyp.py
atup/cast.py
atup/core.py
atup/depr.py
atup/find.py
atup/flag.py
atup/util.py
atup/varg.py
atup-0.0.12.dist-info/LICENSE
atup-0.0.12.dist-info/METADATA
atup-0.0.12.dist-info/WHEEL
atup-0.0.12.dist-info/entry_points.txt
atup-0.0.12.dist-info/top_level.txt
atup-0.0.12.dist-info/RECORD
