Metadata-Version: 2.1
Name: atup
Version: 0.0.12
Summary: atup
Home-page: https://github.com/dsm-72/atup
Author: dsm-72
Author-email: sumner.magruder@yale.edu
License: Apache Software License 2.0
Keywords: atup additional tuple utilities utils tups argument unpacking
Classifier: Development Status :: 4 - Beta
Classifier: Intended Audience :: Developers
Classifier: Natural Language :: English
Classifier: Programming Language :: Python :: 3.11
Classifier: License :: OSI Approved :: Apache Software License
Requires-Python: >=3.11
Provides-Extra: dev
License-File: LICENSE
